running_performance/__init__.py
running_performance/cameron.py
running_performance/exceptions.py
running_performance/purdy.py
running_performance/riegel.py
running_performance/vo2max.py
running_performance-0.2.1.dist-info/LICENSE.md
running_performance-0.2.1.dist-info/METADATA
running_performance-0.2.1.dist-info/WHEEL
running_performance-0.2.1.dist-info/top_level.txt
running_performance-0.2.1.dist-info/RECORD
