Metadata-Version: 2.1
Name: running-performance
Version: 0.2.1
Summary: Running performance indicators and predictors
Home-page: https://github.com/sweat-pain-data/python-running-performance
Author: Christian Wygoda
Author-email: info@wygoda.net
License: MIT License
Keywords: Purdy Points,VO2 Max
Platform: UNKNOWN
Classifier: Programming Language :: Python :: 3
Classifier: License :: OSI Approved :: MIT License
Classifier: Operating System :: OS Independent
